stickytape/__init__.py
stickytape/main.py
stickytape/prelude.py
stickytape/stdlib.py
stickytape-0.2.1.dist-info/LICENSE
stickytape-0.2.1.dist-info/METADATA
stickytape-0.2.1.dist-info/WHEEL
stickytape-0.2.1.dist-info/entry_points.txt
stickytape-0.2.1.dist-info/top_level.txt
stickytape-0.2.1.dist-info/RECORD
