Metadata-Version: 2.1
Name: stickytape
Version: 0.2.1
Summary: Convert Python packages into a single script
Home-page: http://github.com/mwilliamson/stickytape
Author: Michael Williamson
Author-email: mike@zwobble.org
License: BSD-2-Clause
Platform: UNKNOWN
Requires-Python: >=3.4
